IceTeaCCI/entrypoint.py
IceTeaCCI/sql_to_xlsx.py
IceTeaCCI/xlsx_to_sql.py
iceteacci-0.4.4.dist-info/METADATA
iceteacci-0.4.4.dist-info/WHEEL
iceteacci-0.4.4.dist-info/entry_points.txt
iceteacci-0.4.4.dist-info/licenses/LICENSE
iceteacci-0.4.4.dist-info/RECORD
