Metadata-Version: 2.3
Name: IceTeaCCI
Version: 0.4.4
Summary: Tired of fiddling with obscure, confusing SQL files? Take a break. Have some IceTea. IceTea is a tool that converts SQL databases generated by Cumulus CI into Excel, for manual editing, and converts them back to SQL files
Project-URL: Repo, https://github.com/ArdenKolodner/CCI-SQL-XLSX-Importer-Exporter
Author-email: Arden Kolodner <akolodner25@amherst.edu>
Classifier: License :: OSI Approved :: MIT License
Classifier: Operating System :: OS Independent
Classifier: Programming Language :: Python :: 3
Requires-Python: >=3.0
Requires-Dist: openpyxl
Requires-Dist: send2trash
